AUTHORS
LICENSE
MANIFEST.in
README.rst
setup.py
django_thumborstorage/__init__.py
django_thumborstorage/exceptions.py
django_thumborstorage/storages.py
django_thumborstorage.egg-info/PKG-INFO
django_thumborstorage.egg-info/SOURCES.txt
django_thumborstorage.egg-info/dependency_links.txt
django_thumborstorage.egg-info/requires.txt
django_thumborstorage.egg-info/top_level.txt
tests/Makefile
tests/__init__.py
tests/coveragerc
tests/runtests.py
tests/settings.py
tests/images/HannibalSmith.jpg
tests/images/TempletonPeck.jpg
tests/images/bouboune.png
tests/images/gnu.png
tests/regressiontests/__init__.py
tests/regressiontests/storages.py
tests/thumbor_project/env.sh
tests/thumbor_project/initial_data.json
tests/thumbor_project/manage.py
tests/thumbor_project/media/people/HannibalSmith.jpg
tests/thumbor_project/media/people/fs/ChuckNorris.jpg
tests/thumbor_project/my_app/__init__.py
tests/thumbor_project/my_app/admin.py
tests/thumbor_project/my_app/models.py
tests/thumbor_project/my_app/tests.py
tests/thumbor_project/my_app/views.py
tests/thumbor_project/thumbor_project/__init__.py
tests/thumbor_project/thumbor_project/settings.py
tests/thumbor_project/thumbor_project/urls.py
tests/thumbor_project/thumbor_project/wsgi.py