Metadata-Version: 2.1
Name: django-thumborstorage
Version: 2.0.0
Summary: Django custom storage for Thumbor backend.
Home-page: https://github.com/Starou/django-thumborstorage
Author: Stanislas Guerra
Author-email: stanislas.guerra@gmail.com
License: MIT Licence
Project-URL: Source Code, https://github.com/Starou/django-thumborstorage
Project-URL: Issue Tracker, https://github.com/Starou/django-thumborstorage/issues
Platform: UNKNOWN
Classifier: Environment :: Web Environment
Classifier: Framework :: Django
Classifier: Intended Audience :: Developers
Classifier: License :: OSI Approved :: BSD License
Classifier: Operating System :: OS Independent
Classifier: Programming Language :: Python
Classifier: Programming Language :: Python :: 3
Classifier: Programming Language :: Python :: 3.6
Classifier: Programming Language :: Python :: 3.7
Classifier: Programming Language :: Python :: 3.8
Classifier: Programming Language :: Python :: 3.9
Classifier: Topic :: Internet :: WWW/HTTP
Classifier: Topic :: Internet :: WWW/HTTP :: Dynamic Content
License-File: LICENSE
License-File: AUTHORS
